pulka/__init__.py
pulka/__main__.py
pulka/clipboard.py
pulka/derived.py
pulka/dev.py
pulka/session.py
pulka/theme.py
pulka/api/__init__.py
pulka/api/runtime.py
pulka/api/session.py
pulka/cli/__init__.py
pulka/cli/default_generate_presets.toml
pulka/cli/generate.py
pulka/cli/presets.py
pulka/cli/progress.py
pulka/cli/spec.py
pulka/command/builtins.py
pulka/command/parser.py
pulka/command/registry.py
pulka/command/runtime.py
pulka/command/spec.py
pulka/config/__init__.py
pulka/config/feature_flags.py
pulka/config/load.py
pulka/config/settings.py
pulka/core/__init__.py
pulka/core/column_insight.py
pulka/core/errors.py
pulka/core/formatting.py
pulka/core/interfaces.py
pulka/core/plan.py
pulka/core/plan_ops.py
pulka/core/predicate.py
pulka/core/predicate_compiler.py
pulka/core/row_identity.py
pulka/core/row_provider.py
pulka/core/row_provider_cache.py
pulka/core/row_provider_parquet.py
pulka/core/row_provider_sidecar.py
pulka/core/row_provider_streaming.py
pulka/core/row_provider_types.py
pulka/core/sheet.py
pulka/core/sheet_actions.py
pulka/core/sheet_traits.py
pulka/core/source_traits.py
pulka/core/strategy.py
pulka/core/engine/__init__.py
pulka/core/engine/contracts.py
pulka/core/engine/duckdb_adapter.py
pulka/core/engine/polars_adapter.py
pulka/core/engine/viewer_engine.py
pulka/core/jobs/__init__.py
pulka/core/jobs/column_insight_job.py
pulka/core/jobs/duckdb_column_insight_job.py
pulka/core/viewer/__init__.py
pulka/core/viewer/components.py
pulka/core/viewer/plan_controller.py
pulka/core/viewer/public_state.py
pulka/core/viewer/row_count_tracker.py
pulka/core/viewer/search.py
pulka/core/viewer/selection.py
pulka/core/viewer/snapshot_builder.py
pulka/core/viewer/state.py
pulka/core/viewer/terminal.py
pulka/core/viewer/transformation_manager.py
pulka/core/viewer/types.py
pulka/core/viewer/ui_hooks.py
pulka/core/viewer/ui_state.py
pulka/core/viewer/view_stack.py
pulka/core/viewer/viewer.py
pulka/data/csv_checkpoints.py
pulka/data/db.py
pulka/data/export.py
pulka-0.3.0.dist-info/licenses/LICENSE
pulka-0.3.0.dist-info/METADATA
pulka-0.3.0.dist-info/WHEEL
pulka-0.3.0.dist-info/entry_points.txt
pulka-0.3.0.dist-info/top_level.txt
pulka-0.3.0.dist-info/RECORD
