Metadata-Version: 2.4
Name: pulka
Version: 0.3.0
Summary: A tiny, fast VisiData-like tabular viewer for Polars.
Author: Pulka developers
License-Expression: MIT
Project-URL: Homepage, https://github.com/pulka-dev/pulka
Project-URL: Documentation, https://github.com/pulka-dev/pulka#readme
Project-URL: Issues, https://github.com/pulka-dev/pulka/issues
Keywords: polars,dataframe,tui,visualization,analytics
Classifier: Development Status :: 4 - Beta
Classifier: Intended Audience :: Developers
Classifier: Intended Audience :: Science/Research
Classifier: Operating System :: OS Independent
Classifier: Programming Language :: Python
Classifier: Programming Language :: Python :: 3
Classifier: Programming Language :: Python :: 3.12
Classifier: Topic :: Database
Classifier: Topic :: Scientific/Engineering :: Information Analysis
Classifier: Topic :: Utilities
Requires-Python: >=3.12
License-File: LICENSE
Requires-Dist: polars[excel]>=1.16.0
Requires-Dist: prompt-toolkit>=3.0.48
Requires-Dist: rich>=13.7.1
Requires-Dist: pyarrow>=16.0.0
Requires-Dist: pyyaml>=6.0
Requires-Dist: zstandard>=0.22.0
Requires-Dist: xlsxwriter>=3.2.9
Requires-Dist: duckdb>=1.4.3
Provides-Extra: test
Requires-Dist: pytest>=8.4; extra == "test"
Requires-Dist: pytest-randomly>=4.0.1; extra == "test"
Provides-Extra: dev
Requires-Dist: pytest>=8.4; extra == "dev"
Requires-Dist: pytest-randomly>=4.0.1; extra == "dev"
Requires-Dist: ruff>=0.6.0; extra == "dev"
Requires-Dist: prek>=0.1.0; extra == "dev"
Requires-Dist: import-linter>=2.0; extra == "dev"
Requires-Dist: mypy>=1.11; extra == "dev"
Requires-Dist: build>=1.2.2; extra == "dev"
Requires-Dist: twine>=5.1; extra == "dev"
Dynamic: license-file
